{
  "name": "ring",
  "asset_type": "object",
  "sprite": "sprite_ring",
  "visible": true,
  "solid": false,
  "persistent": false,
  "depth": 0,
  "events": {
    "collision_with_obj_person": {
      "actions": [
        {
          "action": "set_sprite",
          "parameters": {
            "sprite": "sound_diamond",
            "subimage": "0"
          }
        },
        {
          "action": "create_random_instance",
          "parameters": {}
        },
        {
          "action": "set_sprite",
          "parameters": {
            "sprite": "sprite_monster_afraid",
            "subimage": "-1",
            "speed": "0"
          }
        },
        {
          "action": "execute_code",
          "parameters": {
            "code": "afraid"
          }
        },
        {
          "action": "if_collision",
          "parameters": {
            "x": "300",
            "y": "0"
          }
        },
        {
          "action": "goto_room",
          "parameters": {
            "room": "20",
            "relative": true
          }
        }
      ],
      "target_object": "obj_person"
    }
  },
  "imported": true,
  "created": "2026-05-23T14:34:56.567174",
  "modified": "2026-05-23T14:34:56.567174"
}